cognitivefactory/interactive_clustering/__init__.py
cognitivefactory/interactive_clustering/clustering/__init__.py
cognitivefactory/interactive_clustering/clustering/abstract.py
cognitivefactory/interactive_clustering/clustering/affinity_propagation.py
cognitivefactory/interactive_clustering/clustering/dbscan.py
cognitivefactory/interactive_clustering/clustering/factory.py
cognitivefactory/interactive_clustering/clustering/hierarchical.py
cognitivefactory/interactive_clustering/clustering/kmeans.py
cognitivefactory/interactive_clustering/clustering/mpckmeans.py
cognitivefactory/interactive_clustering/clustering/spectral.py
cognitivefactory/interactive_clustering/constraints/__init__.py
cognitivefactory/interactive_clustering/constraints/abstract.py
cognitivefactory/interactive_clustering/constraints/binary.py
cognitivefactory/interactive_clustering/constraints/factory.py
cognitivefactory/interactive_clustering/py.typed
cognitivefactory/interactive_clustering/sampling/__init__.py
cognitivefactory/interactive_clustering/sampling/abstract.py
cognitivefactory/interactive_clustering/sampling/clusters_based.py
cognitivefactory/interactive_clustering/sampling/factory.py
cognitivefactory/interactive_clustering/utils/__init__.py
cognitivefactory/interactive_clustering/utils/frequency.py
cognitivefactory/interactive_clustering/utils/preprocessing.py
cognitivefactory/interactive_clustering/utils/vectorization.py
cognitivefactory_interactive_clustering-1.0.0.dist-info/WHEEL
cognitivefactory_interactive_clustering-1.0.0.dist-info/METADATA
cognitivefactory_interactive_clustering-1.0.0.dist-info/licenses/LICENSE.md
cognitivefactory_interactive_clustering-1.0.0.dist-info/RECORD
