Metadata-Version: 2.1
Name: cognitivefactory-interactive-clustering
Version: 1.0.0
Summary: Python package used to apply NLP interactive clustering methods.
License: CECILL-C
Keywords: python,natural-language-processing,clustering,constraints,constrained-clustering-algorithm,interactive-clustering
Author-email: Erwan Schild <erwan.schild@e-i.com>
Requires-Python: >=3.8
Classifier: Development Status :: 5 - Production/Stable
Classifier: Intended Audience :: Developers
Classifier: Programming Language :: Python
Classifier: Programming Language :: Python :: 3
Classifier: Programming Language :: Python :: 3 :: Only
Classifier: Programming Language :: Python :: 3.8
Classifier: Programming Language :: Python :: 3.9
Classifier: Topic :: Documentation
Classifier: Topic :: Software Development
Classifier: Topic :: Software Development :: Documentation
Classifier: Topic :: Utilities
Classifier: Typing :: Typed
Requires-Dist: networkx>=2.6
Requires-Dist: numpy>=1.23.5
Requires-Dist: scikit-learn>=0.24.1
Requires-Dist: scipy>=1.7.3
Requires-Dist: setuptools>=65.5.1
Requires-Dist: spacy<3.5,>=3.4
Project-URL: Changelog, https://cognitivefactory.github.io/interactive-clustering/changelog
Project-URL: Discussions, https://github.com/cognitivefactory/interactive-clustering/discussions
Project-URL: Documentation, https://cognitivefactory.github.io/interactive-clustering
Project-URL: Homepage, https://cognitivefactory.github.io/interactive-clustering
Project-URL: Issues, https://github.com/cognitivefactory/interactive-clustering/issues
Project-URL: Repository, https://github.com/cognitivefactory/interactive-clustering
